dicompare/__init__.py
dicompare/config.py
dicompare/data_utils.py
dicompare/metaschema.json
dicompare/utils.py
dicompare/cli/__init__.py
dicompare/cli/main.py
dicompare/interface/__init__.py
dicompare/interface/web_utils.py
dicompare/io/__init__.py
dicompare/io/dicom.py
dicompare/io/dicom_generator.py
dicompare/io/examcard.py
dicompare/io/json.py
dicompare/io/lxprotocol.py
dicompare/io/pro.py
dicompare/io/special_fields.py
dicompare/processing/__init__.py
dicompare/processing/parallel_utils.py
dicompare/processing/progress_utils.py
dicompare/schema/__init__.py
dicompare/schema/build_schema.py
dicompare/schema/tags.py
dicompare/session/__init__.py
dicompare/session/acquisition.py
dicompare/session/mapping.py
dicompare/tests/__init__.py
dicompare/tests/generate_test_dataset.py
dicompare/tests/test_acquisition_assignment.py
dicompare/tests/test_cli.py
dicompare/tests/test_compliance.py
dicompare/tests/test_compliance_series_fix.py
dicompare/tests/test_compliance_unified.py
dicompare/tests/test_data_utils.py
dicompare/tests/test_dicom_factory.py
dicompare/tests/test_dicom_generator.py
dicompare/tests/test_examcard.py
dicompare/tests/test_generate_schema.py
dicompare/tests/test_helpers.py
dicompare/tests/test_integration_hybrid.py
dicompare/tests/test_io.py
dicompare/tests/test_lxprotocol.py
dicompare/tests/test_mapping.py
dicompare/tests/test_multiband_extraction.py
dicompare/tests/test_parallel_utils.py
dicompare/tests/test_pro_files.py
dicompare/tests/test_ref_dicom.py
dicompare/tests/test_schema_integration.py
dicompare/tests/test_schema_validation.py
dicompare/tests/test_serialization.py
dicompare/tests/test_special_fields.py
dicompare/tests/test_tags.py
dicompare/tests/test_utils_core.py
dicompare/tests/test_validation_core.py
dicompare/tests/test_validation_dynamic.py
dicompare/tests/test_validation_helpers.py
dicompare/tests/test_visualization.py
dicompare/tests/test_web_utils.py
dicompare/tests/fixtures/__init__.py
dicompare/tests/fixtures/fixtures.py
dicompare-0.1.45.dist-info/licenses/LICENSE
dicompare-0.1.45.dist-info/METADATA
dicompare-0.1.45.dist-info/WHEEL
dicompare-0.1.45.dist-info/entry_points.txt
dicompare-0.1.45.dist-info/top_level.txt
dicompare-0.1.45.dist-info/RECORD
