Metadata-Version: 2.4
Name: dicompare
Version: 0.1.45
Summary: A tool for checking DICOM compliance against a template
Home-page: https://github.com/astewartau/dicompare
Author: Ashley Stewart
Keywords: DICOM compliance validation medical imaging
Classifier: Programming Language :: Python :: 3
Classifier: License :: OSI Approved :: MIT License
Classifier: Operating System :: OS Independent
Requires-Python: >=3.8
License-File: LICENSE
Requires-Dist: pydicom==2.4.4
Requires-Dist: pandas
Requires-Dist: tabulate
Requires-Dist: scipy
Requires-Dist: tqdm
Requires-Dist: nibabel
Requires-Dist: twixtools
Requires-Dist: jsonschema
Provides-Extra: interactive
Requires-Dist: curses; extra == "interactive"
Provides-Extra: test
Requires-Dist: pytest-asyncio; extra == "test"
Dynamic: author
Dynamic: classifier
Dynamic: description
Dynamic: description-content-type
Dynamic: home-page
Dynamic: keywords
Dynamic: license-file
Dynamic: provides-extra
Dynamic: requires-dist
Dynamic: requires-python
Dynamic: summary
